rajsiri/__init__.py
rajsiri/rajsiri.py
rajsiri-0.1.1.dist-info/METADATA
rajsiri-0.1.1.dist-info/WHEEL
rajsiri-0.1.1.dist-info/entry_points.txt
rajsiri-0.1.1.dist-info/top_level.txt
rajsiri-0.1.1.dist-info/RECORD
