Metadata-Version: 2.1
Name: rajsiri
Version: 0.1.1
Summary: Learning Module
Home-page: UNKNOWN
Author: Rajesh Kamireddy Author
Author-email: rajesh17mca@gmail.com
License: UNKNOWN
Platform: UNKNOWN
Requires-Python: >=3.6
